caustic/cst/__init__.py
caustic/cst/block.py
caustic/cst/procedure.py
caustic/cst/serialize.py
caustic/cst/typedecl.py
caustic/cst/expressions/__init__.py
caustic/cst/expressions/atoms.py
caustic/cst/expressions/operators.py
caustic/cst/statements/__init__.py
caustic/cst/statements/objects.py
caustic.cst-2.1.1.dist-info/LICENSE
caustic.cst-2.1.1.dist-info/METADATA
caustic.cst-2.1.1.dist-info/WHEEL
caustic.cst-2.1.1.dist-info/top_level.txt
caustic.cst-2.1.1.dist-info/RECORD
