Metadata-Version: 2.1
Name: caustic.cst
Version: 2.1.1
Summary: Caustic's Abstract Syntax Tree, or CST
Author: Shae.c32
Project-URL: Homepage, https://codeberg.org/Caustic/CausticAST
Project-URL: Issues, https://codeberg.org/Caustic/CausticAST/issues
Keywords: caustic,language,parser,ast,syntax,tree
Classifier: Development Status :: 5 - Production/Stable
Classifier: Intended Audience :: Developers
Classifier: License :: OSI Approved :: Apache Software License
Classifier: Natural Language :: English
Classifier: Programming Language :: Other
Classifier: Topic :: File Formats
Classifier: Topic :: Software Development
Classifier: Topic :: Software Development :: Compilers
Classifier: Topic :: Software Development :: Documentation
Classifier: Topic :: Software Development :: Interpreters
Requires-Python: >=3.9
License-File: LICENSE
